{
    "particles": [
        "particles/p1.png",
        "particles/p2.png",
        "particles/p3.png",
        "particles/p4.png",
        "particles/p5.png",
        "particles/p6.png",
        "particles/p7.png",
        "particles/p8.png",
        "particles/p9.png",
        "particles/p10.png"
    ],
    "textures": [
        {
            "name": "bkgd:title",
            "path": "start_screen_without_btn.jpg"
        },
        {
            "name": "bkgd:end_screen",
            "path": "overlay.png"
        },
        {
            "name": "btn:title",
            "path": "start_btn_default.png"
        },
        {
            "name": "btn:title_hover",
            "path": "start_btn_hover.png"
        },
        {
            "name": "icon:score_back",
            "path": "score_back.png"
        },
        {
            "name": "icon:atk_back",
            "path": "atk_back.png"
        },
        {
            "name": "icon:place_circle",
            "path": "circle_mask.png"
        },
        {
            "name": "icon:loading",
            "path": "loading.jpg"
        },
        {
            "name": "icon:victory",
            "path": "victory.jpg"
        }, 
        {
            "name": "icon:defeat",
            "path": "defeat.jpg"
        },

        {
            "name": "btn:option",
            "path": "option.png"
        },
        {
            "name": "btn:go",
            "path": "go_btn.png"
        },
        {
            "name": "icon:option_selected",
            "path": "option_selected.png"
        },
        {
            "name": "icon:select_leaf_txt",
            "path": "select_your_leaf_text.png"
        },
        {
            "name": "icon:select_leaf_color_txt",
            "path": "select_leaf_color_text.png"
        },
        {
            "name": "icon:select_wood_color_txt",
            "path": "select_wood_color_text.png"
        },
        {
            "name": "mask:none",
            "path": "default_mask.png"
        },
        {
            "name": "mask:circle",
            "path": "circle_mask.png"
        }
    ]
}